Metadata-Version: 2.1
Name: verifonePED
Version: 0.1.0
Summary: Sends control commands to Verifone pin entry devices
Home-page: https://github.com/geftactics/python-verifonePED
Download-URL: https://github.com/geftactics/python-verifonePED/archive/0.1.0.tar.gz
Author: Geoff Kendal
Author-email: Geoff@squiggle.org
License: MIT
License-File: LICENCE.txt
